MANIFEST.in
document_data.xml
document_demo.xml
document_view.xml
setup.py
./__init__.py
./__openerp__.py
./content_index.py
./document.py
./odt2txt.py
./std_index.py
./test_cindex.py
./report/__init__.py
./report/document_report.py
./wizard/__init__.py
./wizard/document_configuration.py
doc/access_permissions.rst
i18n/ar.po
i18n/bg.po
i18n/bs.po
i18n/ca.po
i18n/cs.po
i18n/da.po
i18n/de.po
i18n/document.pot
i18n/el.po
i18n/es.po
i18n/es_AR.po
i18n/es_CR.po
i18n/es_EC.po
i18n/es_MX.po
i18n/es_PY.po
i18n/es_VE.po
i18n/et.po
i18n/fi.po
i18n/fr.po
i18n/gl.po
i18n/gu.po
i18n/he.po
i18n/hi.po
i18n/hi_HI.po
i18n/hr.po
i18n/hu.po
i18n/id.po
i18n/it.po
i18n/ja.po
i18n/ko.po
i18n/lt.po
i18n/lv.po
i18n/mk.po
i18n/mn.po
i18n/nb.po
i18n/nl.po
i18n/nl_BE.po
i18n/pl.po
i18n/pt.po
i18n/pt_BR.po
i18n/ro.po
i18n/ru.po
i18n/sk.po
i18n/sl.po
i18n/sq.po
i18n/sr.po
i18n/sr@latin.po
i18n/sv.po
i18n/tlh.po
i18n/tr.po
i18n/uk.po
i18n/vi.po
i18n/zh_CN.po
i18n/zh_HK.po
i18n/zh_TW.po
images/1_directories.jpeg
images/2_storage_media.jpeg
images/3_directories_structure.jpeg
openerp_document.egg-info/PKG-INFO
openerp_document.egg-info/SOURCES.txt
openerp_document.egg-info/dependency_links.txt
openerp_document.egg-info/requires.txt
openerp_document.egg-info/top_level.txt
report/document_report_view.xml
security/document_security.xml
security/ir.model.access.csv
static/src/js/document.js
test/document_test.yml
test/document_test2.yml
wizard/document_configuration_view.xml